amortize/__init__.py
amortize/amortize.py
amortize/calc.py
amortize-0.0.9.dist-info/entry_points.txt
amortize-0.0.9.dist-info/WHEEL
amortize-0.0.9.dist-info/METADATA
amortize-0.0.9.dist-info/RECORD
