Metadata-Version: 2.1
Name: amortize
Version: 0.0.9
Summary: Easy-to-use Python Library for Amortization Schedule and Refinance
License: MIT
Keywords: mortgage,amortization,loan,refinance
Author: ahmetserguns
Requires-Python: >=3.8,<4.0
Classifier: Development Status :: 5 - Production/Stable
Classifier: License :: OSI Approved :: MIT License
Classifier: Programming Language :: Python :: 3
Classifier: Programming Language :: Python :: 3.6
Classifier: Programming Language :: Python :: 3.7
Classifier: Programming Language :: Python :: 3.8
Classifier: Programming Language :: Python :: 3.9
Classifier: Topic :: Office/Business :: Financial :: Accounting
Classifier: Topic :: Scientific/Engineering :: Mathematics
Classifier: Topic :: Software Development :: Libraries :: Python Modules
Requires-Dist: numpy-financial (>=1.0.0,<2.0.0)
Requires-Dist: pandas (>=1.2.1,<2.0.0)
Requires-Dist: tabulate (>=0.8.7,<0.9.0)
